PyWinRegistry/__init__.py
PyWinRegistry/processor.py
pywinregistry-0.0.1.dist-info/METADATA
pywinregistry-0.0.1.dist-info/WHEEL
pywinregistry-0.0.1.dist-info/top_level.txt
pywinregistry-0.0.1.dist-info/RECORD
