Metadata-Version: 2.1
Name: pywinregistry
Version: 0.0.1
Summary: A windows registry script generator written in pure Python.
Home-page: https://github.com/songs18/PyWinRegistry
Author: songs18
Author-email: sounghaohao@gmail.com
License: MIT
